TencentExmail-0.1.2.dist-info/DESCRIPTION.rst
TencentExmail-0.1.2.dist-info/METADATA
TencentExmail-0.1.2.dist-info/RECORD
TencentExmail-0.1.2.dist-info/WHEEL
TencentExmail-0.1.2.dist-info/metadata.json
TencentExmail-0.1.2.dist-info/top_level.txt
tencent_exmail/__init__.py
tencent_exmail/BaseRequest/BaseHttpRequest.py
tencent_exmail/BaseRequest/__init__.py
tencent_exmail/ContactManagement/DepartmentMangement.py
tencent_exmail/ContactManagement/GroupManagement.py
tencent_exmail/ContactManagement/UserManagement.py
tencent_exmail/ContactManagement/__init__.py
tencent_exmail/FunctionSetting/FunctionAttribute.py
tencent_exmail/FunctionSetting/__init__.py
tencent_exmail/Initiative/__init__.py
tencent_exmail/Initiative/get_access_token.py
tencent_exmail/Login/LoginMail.py
tencent_exmail/Login/__init__.py
tencent_exmail/NewMailNotification/GetMailUnread.py
tencent_exmail/NewMailNotification/__init__.py
tencent_exmail/SystemLog/CheckBatchJob.py
tencent_exmail/SystemLog/CheckMail.py
tencent_exmail/SystemLog/CheckMailInfo.py
tencent_exmail/SystemLog/CheckOperationLog.py
tencent_exmail/SystemLog/CheckUserLogin.py
tencent_exmail/SystemLog/__init__.py
tests/__init__.py
tests/test_access_token.py
tests/test_batch_job.py
tests/test_check_mail.py
tests/test_check_mail_info.py
tests/test_check_operation_log.py
tests/test_departmentManagement.py
tests/test_functionAttribute.py
tests/test_getMailUnread.py
tests/test_groupManagement.py
tests/test_login_mail.py
tests/test_userManagement.py
tests/test_userlogin.py
