Metadata-Version: 2.0
Name: TencentExmail
Version: 0.1.2
Summary: Python Tencent Exmail API
Home-page: https://github.com/sunhailin-Leo/TencentExmailAPI
Author: sunhailin-Leo
Author-email: 379978424@qq.com
License: Apache License 2.0
Keywords: Tecent,Exmail
Platform: UNKNOWN
Classifier: Development Status :: 4 - Beta
Classifier: Environment :: Console
Classifier: Intended Audience :: Developers
Classifier: License :: OSI Approved :: MIT License
Classifier: Operating System :: OS Independent
Classifier: Programming Language :: Python
Classifier: Programming Language :: Python :: Implementation
Classifier: Programming Language :: Python :: 3
Classifier: Programming Language :: Python :: 3.4
Classifier: Programming Language :: Python :: 3.5
Classifier: Programming Language :: Python :: 3.6
Classifier: Topic :: Software Development :: Libraries
Requires-Dist: requests
